purplship/mappers/boxknight/__init__.py
purplship/mappers/boxknight/mapper.py
purplship/mappers/boxknight/proxy.py
purplship/mappers/boxknight/settings.py
purplship/providers/boxknight/__init__.py
purplship/providers/boxknight/error.py
purplship/providers/boxknight/pickup/__init__.py
purplship/providers/boxknight/pickup/cancel.py
purplship/providers/boxknight/pickup/create.py
purplship/providers/boxknight/pickup/update.py
purplship/providers/boxknight/rate.py
purplship/providers/boxknight/shipment/__init__.py
purplship/providers/boxknight/shipment/cancel.py
purplship/providers/boxknight/shipment/create.py
purplship/providers/boxknight/units.py
purplship/providers/boxknight/utils.py
purplship.boxknight-2021.10.1.dist-info/WHEEL
purplship.boxknight-2021.10.1.dist-info/METADATA
purplship.boxknight-2021.10.1.dist-info/RECORD
